LICENSE
README.md
setup.py
dask_actor_singleton/__init__.py
dask_actor_singleton.egg-info/PKG-INFO
dask_actor_singleton.egg-info/SOURCES.txt
dask_actor_singleton.egg-info/dependency_links.txt
dask_actor_singleton.egg-info/requires.txt
dask_actor_singleton.egg-info/top_level.txt
test/test_singleton.py