Metadata-Version: 2.1
Name: dask-actor-singleton
Version: 1.3.4
Summary: Helper library to allocate and retrieve singleton actors in Dask
Home-page: https://github.com/wwoods/dask-actor-singleton
Author: Walt Woods
Author-email: woodswalben@gmail.com
Classifier: Programming Language :: Python :: 3
Classifier: License :: OSI Approved :: MIT License
Classifier: Operating System :: OS Independent
License-File: LICENSE
